proxynova_scraper/__init__.py
proxynova_scraper/proxynova.py
proxynova_scraper/scrapper.py
proxynova_scraper/utils.py
proxynova_scraper-0.1.dist-info/LICENSE
proxynova_scraper-0.1.dist-info/METADATA
proxynova_scraper-0.1.dist-info/WHEEL
proxynova_scraper-0.1.dist-info/top_level.txt
proxynova_scraper-0.1.dist-info/RECORD
