Metadata-Version: 2.1
Name: proxynova-scraper
Version: 0.1
Summary: Package to get proxies from proxynova.com via web scraping
Author: German Martinez Solis
Author-email: german.mtz.solis@gmail.com
License: MIT
Project-URL: Bug Tracker, https://github.com/GermanMtzmx/proxynova_scraper
Platform: UNKNOWN
Classifier: Programming Language :: Python :: 3.8
Classifier: License :: OSI Approved :: MIT License
Classifier: Operating System :: OS Independent
Requires-Python: >=3
License-File: LICENSE
Requires-Dist: bs4
Requires-Dist: html5lib
Requires-Dist: pyppeteer
Requires-Dist: asyncio
Requires-Dist: unidecode
